LICENSE.txt
MANIFEST.in
README.rst
setup.cfg
setup.py
doc/Makefile
doc/conf.py
doc/index.rst
doc/objects.inv
doc/trackapps.1
doc/rst/install.rst
doc/rst/module.rst
doc/rst/refman.rst
doc/rst/tutor.rst
doc/rst/install/extensions.rst
doc/rst/install/ext/trackapps.rst
doc/rst/module/extensions.rst
doc/rst/module/ext/trackapps/bugzilla.rst
doc/rst/module/ext/trackapps/jira.rst
doc/rst/module/ext/trackapps/main.rst
doc/rst/module/ext/trackapps/mantis.rst
doc/rst/module/ext/trackapps/qc.rst
doc/rst/module/ext/trackapps/testlink.rst
doc/rst/module/ext/trackapps/trac.rst
doc/rst/module/ext/trackapps/trackapps.rst
doc/rst/refman/ext/trackapps.rst
doc/rst/tutor/extensions.rst
doc/rst/tutor/ext/trackapps/trackapps.rst
doc/rst/tutor/ext/trackapps/tut1_qc.rst
doc/rst/tutor/ext/trackapps/tut2_bugzilla.rst
doc/rst/tutor/ext/trackapps/tut3_mantis.rst
doc/rst/tutor/ext/trackapps/tut4_trac.rst
doc/rst/tutor/ext/trackapps/tut5_jira.rst
doc/rst/tutor/ext/trackapps/tut6_testlink.rst
etc/hydratk/conf.d/hydratk-ext-trackapps.conf
src/hydratk/__init__.py
src/hydratk/extensions/__init__.py
src/hydratk/extensions/trackapps/__init__.py
src/hydratk/extensions/trackapps/bootstrapper.py
src/hydratk/extensions/trackapps/bugzilla.py
src/hydratk/extensions/trackapps/jira.py
src/hydratk/extensions/trackapps/mantis.py
src/hydratk/extensions/trackapps/qc.py
src/hydratk/extensions/trackapps/testlink.py
src/hydratk/extensions/trackapps/trac.py
src/hydratk/extensions/trackapps/trackapps.py
src/hydratk/extensions/trackapps/translation/__init__.py
src/hydratk/extensions/trackapps/translation/info.py
src/hydratk/extensions/trackapps/translation/cs/__init__.py
src/hydratk/extensions/trackapps/translation/cs/help.py
src/hydratk/extensions/trackapps/translation/cs/messages.py
src/hydratk/extensions/trackapps/translation/en/__init__.py
src/hydratk/extensions/trackapps/translation/en/help.py
src/hydratk/extensions/trackapps/translation/en/messages.py
src/hydratk_ext_trackapps.egg-info/PKG-INFO
src/hydratk_ext_trackapps.egg-info/SOURCES.txt
src/hydratk_ext_trackapps.egg-info/dependency_links.txt
src/hydratk_ext_trackapps.egg-info/entry_points.txt
src/hydratk_ext_trackapps.egg-info/not-zip-safe
src/hydratk_ext_trackapps.egg-info/top_level.txt
tests/travis.yoda
